[[[{"1": 9}, {"2": 2}], [0, 2, 10, 12, 38, 42, 62, 72, 76, 78, 91, 117, 136, 152, 158, 160, 175, 209, 237, 245], 20], [[{"2": 2}, {"1": 9}], [1, 9, 11, 37, 41, 61, 71, 75, 77, 90, 116, 135, 151, 157, 159, 174, 236, 244], 18], [[{"2": 2}, {"1": 4}], [3, 29, 39, 69, 73, 79, 81, 83, 85, 92, 118, 180, 184, 202, 222], 15], [[{"1": 4}, {"3": 2}], [4, 119], 2], [[{"3": 2}, {"2": 2}], [5, 36, 132], 3], [[{"2": 2}, {"3": 2}], [6, 31, 87, 131, 165], 5], [[{"3": 2}, {"1": 2}], [7, 32, 88], 3], [[{"1": 2}, {"2": 2}], [8, 16, 66, 89, 97, 148, 162, 171, 189, 199, 201, 205, 213, 217, 219, 221, 243], 17], [[{"2": 2}, {"1": 40}], [13, 59, 98], 3], [[{"1": 40}, {"2": 2}], [14, 60], 2], [[{"2": 2}, {"1": 2}], [15, 65, 96, 104, 147, 161, 188, 198, 200, 204, 212, 216, 218, 220], 14], [[{"2": 2}, {"1": 15}], [17, 27, 51, 112, 123, 129, 133, 139, 143, 149, 155, 168, 178, 190, 196, 206, 210, 234], 18], [[{"1": 15}, {"2": 2}], [18, 22, 28, 109, 113, 124, 130, 134, 144, 150, 156, 179, 191, 197, 211], 15], [[{"2": 2}, {"1": 20}], [19, 49, 63, 137, 230], 5], [[{"2": 4}, {"1": 15}], [21, 108], 2], [[{"2": 2}, {"1": 200}], [23, 145, 192], 3], [[{"2": 4}, {"1": 30}], [25, 141], 2], [[{"1": 30}, {"2": 2}], [26, 44, 46, 95, 115, 142, 183, 187, 195], 9], [[{"1": 4}, {"2": 2}], [30, 40, 70, 74, 80, 82, 84, 86, 93, 128, 167, 181, 185, 203], 14], [[{"1": 2}, {"2": 4}], [33, 101, 105], 3], [[{"2": 4}, {"1": 2}], [34, 100, 170], 3], [[{"2": 2}, {"1": 30}], [43, 45, 94, 114, 182, 186, 194], 7], [[{"2": 2}, {"1": 60}], [47, 57, 110, 153], 4], [[{"1": 60}, {"2": 2}], [48, 56, 58, 111, 154], 5], [[{"1": 20}, {"2": 2}], [50, 64, 138], 3], [[{"1": 15}, {"2": 4}], [52, 140, 169], 3], [[{"2": 2}, {"1": 6}], [67, 125, 163, 172, 176], 5], [[{"1": 6}, {"2": 2}], [68, 164, 173, 177], 4], [[{"1": 40}, {"2": 4}], [99, 107], 2], [[{"1": 9}, {"2": 2}, {"1": 9}], [0, 10, 76, 158], 4], [[{"2": 2}, {"1": 9}, {"2": 2}], [1, 9, 11, 37, 41, 61, 71, 75, 77, 90, 116, 135, 151, 157, 159, 174, 236, 244], 18], [[{"1": 9}, {"2": 2}, {"1": 4}], [2, 38, 72, 78, 91, 117], 6], [[{"2": 2}, {"1": 4}, {"3": 2}], [3, 118], 2], [[{"2": 2}, {"3": 2}, {"1": 2}], [6, 31, 87], 3], [[{"3": 2}, {"1": 2}, {"2": 2}], [7, 88], 2], [[{"1": 2}, {"2": 2}, {"1": 9}], [8, 89], 2], [[{"2": 2}, {"1": 40}, {"2": 2}], [13, 59], 2], [[{"2": 2}, {"1": 2}, {"2": 2}], [15, 65, 96, 147, 161, 188, 198, 200, 204, 212, 216, 218, 220], 13], [[{"1": 2}, {"2": 2}, {"1": 15}], [16, 148, 189, 205], 4], [[{"2": 2}, {"1": 15}, {"2": 2}], [17, 27, 112, 123, 129, 133, 143, 149, 155, 178, 190, 196, 210], 13], [[{"2": 4}, {"1": 15}, {"2": 2}], [21, 108], 2], [[{"1": 15}, {"2": 2}, {"1": 200}], [22, 144, 191], 3], [[{"2": 4}, {"1": 30}, {"2": 2}], [25, 141], 2], [[{"1": 30}, {"2": 2}, {"1": 15}], [26, 142, 195], 3], [[{"1": 15}, {"2": 2}, {"1": 4}], [28, 179], 2], [[{"2": 2}, {"1": 4}, {"2": 2}], [29, 39, 69, 73, 79, 81, 83, 85, 92, 180, 184, 202], 12], [[{"1": 4}, {"2": 2}, {"3": 2}], [30, 86], 2], [[{"1": 4}, {"2": 2}, {"1": 9}], [40, 70, 74], 3], [[{"2": 2}, {"1": 30}, {"2": 2}], [43, 94, 114, 182, 186, 194], 6], [[{"2": 2}, {"1": 60}, {"2": 2}], [47, 57, 110, 153], 4], [[{"2": 2}, {"1": 20}, {"2": 2}], [49, 63, 137], 3], [[{"1": 20}, {"2": 2}, {"1": 15}], [50, 138], 2], [[{"2": 2}, {"1": 15}, {"2": 4}], [51, 139, 168], 3], [[{"1": 9}, {"2": 2}, {"1": 20}], [62, 136], 2], [[{"1": 2}, {"2": 2}, {"1": 6}], [66, 162, 171], 3], [[{"2": 2}, {"1": 6}, {"2": 2}], [67, 163, 172, 176], 4], [[{"1": 4}, {"2": 2}, {"1": 4}], [80, 84], 2], [[{"1": 9}, {"2": 2}, {"1": 9}, {"2": 2}], [0, 10, 76, 158], 4], [[{"2": 2}, {"1": 9}, {"2": 2}, {"1": 4}], [1, 37, 71, 77, 90, 116], 6], [[{"1": 9}, {"2": 2}, {"1": 4}, {"3": 2}], [2, 117], 2], [[{"2": 2}, {"3": 2}, {"1": 2}, {"2": 2}], [6, 87], 2], [[{"3": 2}, {"1": 2}, {"2": 2}, {"1": 9}], [7, 88], 2], [[{"1": 2}, {"2": 2}, {"1": 9}, {"2": 2}], [8, 89], 2], [[{"2": 2}, {"1": 9}, {"2": 2}, {"1": 9}], [9, 75, 157], 3], [[{"2": 2}, {"1": 2}, {"2": 2}, {"1": 15}], [15, 147, 188, 204], 4], [[{"1": 2}, {"2": 2}, {"1": 15}, {"2": 2}], [16, 148, 189], 3], [[{"2": 4}, {"1": 30}, {"2": 2}, {"1": 15}], [25, 141], 2], [[{"1": 30}, {"2": 2}, {"1": 15}, {"2": 2}], [26, 142, 195], 3], [[{"2": 2}, {"1": 15}, {"2": 2}, {"1": 4}], [27, 178], 2], [[{"1": 15}, {"2": 2}, {"1": 4}, {"2": 2}], [28, 179], 2], [[{"2": 2}, {"1": 4}, {"2": 2}, {"3": 2}], [29, 85], 2], [[{"1": 4}, {"2": 2}, {"3": 2}, {"1": 2}], [30, 86], 2], [[{"1": 9}, {"2": 2}, {"1": 4}, {"2": 2}], [38, 72, 78, 91], 4], [[{"2": 2}, {"1": 4}, {"2": 2}, {"1": 9}], [39, 69, 73], 3], [[{"1": 4}, {"2": 2}, {"1": 9}, {"2": 2}], [40, 70, 74], 3], [[{"2": 2}, {"1": 20}, {"2": 2}, {"1": 15}], [49, 137], 2], [[{"1": 20}, {"2": 2}, {"1": 15}, {"2": 4}], [50, 138], 2], [[{"2": 2}, {"1": 9}, {"2": 2}, {"1": 20}], [61, 135], 2], [[{"1": 9}, {"2": 2}, {"1": 20}, {"2": 2}], [62, 136], 2], [[{"2": 2}, {"1": 2}, {"2": 2}, {"1": 6}], [65, 161], 2], [[{"1": 2}, {"2": 2}, {"1": 6}, {"2": 2}], [66, 162, 171], 3], [[{"2": 2}, {"1": 4}, {"2": 2}, {"1": 4}], [79, 83], 2], [[{"1": 4}, {"2": 2}, {"1": 4}, {"2": 2}], [80, 84], 2], [[{"1": 9}, {"2": 2}, {"1": 9}, {"2": 2}, {"1": 4}], [0, 76], 2], [[{"2": 2}, {"1": 9}, {"2": 2}, {"1": 4}, {"3": 2}], [1, 116], 2], [[{"2": 2}, {"3": 2}, {"1": 2}, {"2": 2}, {"1": 9}], [6, 87], 2], [[{"3": 2}, {"1": 2}, {"2": 2}, {"1": 9}, {"2": 2}], [7, 88], 2], [[{"2": 2}, {"1": 9}, {"2": 2}, {"1": 9}, {"2": 2}], [9, 75, 157], 3], [[{"2": 2}, {"1": 2}, {"2": 2}, {"1": 15}, {"2": 2}], [15, 147, 188], 3], [[{"2": 4}, {"1": 30}, {"2": 2}, {"1": 15}, {"2": 2}], [25, 141], 2], [[{"2": 2}, {"1": 15}, {"2": 2}, {"1": 4}, {"2": 2}], [27, 178], 2], [[{"2": 2}, {"1": 4}, {"2": 2}, {"3": 2}, {"1": 2}], [29, 85], 2], [[{"2": 2}, {"1": 9}, {"2": 2}, {"1": 4}, {"2": 2}], [37, 71, 77, 90], 4], [[{"1": 9}, {"2": 2}, {"1": 4}, {"2": 2}, {"1": 9}], [38, 72], 2], [[{"2": 2}, {"1": 4}, {"2": 2}, {"1": 9}, {"2": 2}], [39, 69, 73], 3], [[{"2": 2}, {"1": 20}, {"2": 2}, {"1": 15}, {"2": 4}], [49, 137], 2], [[{"2": 2}, {"1": 9}, {"2": 2}, {"1": 20}, {"2": 2}], [61, 135], 2], [[{"2": 2}, {"1": 2}, {"2": 2}, {"1": 6}, {"2": 2}], [65, 161], 2], [[{"2": 2}, {"3": 2}, {"1": 2}, {"2": 2}, {"1": 9}, {"2": 2}], [6, 87], 2], [[{"2": 2}, {"1": 9}, {"2": 2}, {"1": 4}, {"2": 2}, {"1": 9}], [37, 71], 2], [[{"1": 9}, {"2": 2}, {"1": 4}, {"2": 2}, {"1": 9}, {"2": 2}], [38, 72], 2], [[{"2": 2}, {"1": 9}, {"2": 2}, {"1": 4}, {"2": 2}, {"1": 9}, {"2": 2}], [37, 71], 2]]