[[[{"2": 4}, {"3": 3}], [0, 81, 143], 3], [[{"3": 3}, {"4": 1}], [1, 216, 233], 3], [[{"4": 1}, {"5": 2}], [2, 106], 2], [[{"3": 1}, {"2": 2}], [7, 128, 140, 162, 375, 456], 6], [[{"2": 2}, {"3": 1}], [8, 23, 75, 141, 240, 347, 356, 443, 521], 9], [[{"4": 2}, {"3": 1}], [10, 114], 2], [[{"3": 1}, {"2": 1}], [11, 24, 76, 96, 115, 138, 227, 243, 274, 438, 444, 462, 508, 510, 545, 558], 16], [[{"2": 1}, {"3": 3}], [12, 25, 167, 232, 450], 5], [[{"3": 3}, {"2": 2}], [13, 365, 520, 528], 4], [[{"2": 2}, {"1": 2}], [14, 59, 63, 129, 301, 325, 343, 551, 583, 603], 10], [[{"3": 2}, {"2": 2}], [16, 111, 239, 458, 526], 5], [[{"2": 2}, {"3": 2}], [17, 230, 457, 529], 4], [[{"3": 2}, {"2": 3}], [18, 119, 428, 512], 4], [[{"2": 3}, {"3": 1}], [19, 27, 99, 127, 213, 420, 557], 7], [[{"3": 1}, {"4": 1}], [20, 105, 237, 247, 448], 5], [[{"3": 3}, {"2": 3}], [26, 168], 2], [[{"2": 12}, {"1": 1}], [29, 311], 2], [[{"1": 1}, {"2": 1}], [30, 38, 154, 160, 184, 210, 252, 264, 284, 290, 328, 340, 377, 407, 452, 554, 560, 570, 576], 19], [[{"2": 1}, {"3": 1}], [31, 39, 83, 139, 161, 246, 374, 509, 540, 544], 10], [[{"1": 3}, {"2": 3}], [36, 132, 174, 190, 250], 5], [[{"2": 3}, {"1": 1}], [37, 41, 222, 251, 271], 5], [[{"3": 1}, {"2": 3}], [40, 126, 214, 522, 548], 5], [[{"1": 1}, {"2": 15}], [42, 200], 2], [[{"1": 1}, {"2": 10}], [44, 280], 2], [[{"1": 4}, {"2": 2}], [46, 68, 342, 500, 572], 5], [[{"2": 2}, {"1": 1}], [47, 69, 183, 269, 293, 352, 354, 368, 376, 382, 406, 553], 12], [[{"1": 1}, {"2": 4}], [48, 146, 150, 219, 223, 294, 393, 424, 484, 534], 10], [[{"2": 4}, {"1": 2}], [49, 151, 295, 335, 563], 5], [[{"1": 2}, {"2": 7}], [50, 336, 389, 524], 4], [[{"1": 4}, {"2": 4}], [52, 504], 2], [[{"2": 4}, {"1": 21}], [53, 491], 2], [[{"1": 21}, {"2": 1}], [54, 492], 2], [[{"1": 2}, {"2": 1}], [60, 123, 166, 198, 266, 326, 344, 349, 385, 466, 514], 11], [[{"2": 1}, {"1": 1}], [61, 88, 97, 124, 185, 199, 228, 263, 267, 285, 289, 291, 299, 327, 339, 345, 380, 423, 439, 445, 463, 483, 533, 559], 24], [[{"1": 1}, {"2": 2}], [62, 229, 268, 286, 292, 300, 346, 353, 355, 381, 440], 11], [[{"1": 2}, {"2": 13}], [64, 158], 2], [[{"3": 4}, {"2": 1}], [66, 338, 543], 3], [[{"2": 1}, {"1": 4}], [67, 171, 341, 469, 503, 515, 555], 7], [[{"1": 1}, {"2": 13}], [70, 272], 2], [[{"2": 13}, {"1": 2}], [71, 157], 2], [[{"1": 2}, {"2": 6}], [72, 282, 478], 3], [[{"4": 1}, {"3": 1}], [79, 95, 234, 248], 4], [[{"3": 1}, {"2": 4}], [80, 142, 206, 241, 357], 5], [[{"3": 3}, {"2": 1}], [82, 170], 2], [[{"3": 1}, {"1": 3}], [84, 249], 2], [[{"1": 3}, {"2": 4}], [85, 136, 208, 334, 395], 5], [[{"2": 4}, {"3": 6}], [86, 535], 2], [[{"2": 1}, {"3": 2}], [93, 110, 511], 3], [[{"1": 1}, {"2": 3}], [98, 186, 221, 270, 308, 312, 383, 434, 464], 9], [[{"3": 3}, {"2": 4}], [103, 144], 2], [[{"2": 4}, {"3": 1}], [104, 137, 224, 242], 4], [[{"4": 1}, {"2": 1}], [121, 258, 449], 3], [[{"2": 1}, {"1": 2}], [122, 165, 211, 259, 265, 275, 350, 388], 8], [[{"1": 2}, {"2": 4}], [130, 152, 411], 3], [[{"2": 4}, {"1": 3}], [131, 207, 394], 3], [[{"2": 3}, {"1": 3}], [133, 173, 187, 191], 4], [[{"1": 3}, {"2": 2}], [134, 188, 367, 442], 4], [[{"2": 2}, {"1": 3}], [135, 189, 287, 366, 441, 459], 6], [[{"2": 4}, {"1": 1}], [145, 153, 209, 220, 392, 412], 6], [[{"2": 5}, {"1": 1}], [149, 195, 471], 3], [[{"2": 1}, {"1": 3}], [155, 193, 317, 331, 333, 378], 6], [[{"1": 5}, {"2": 1}], [164, 387], 2], [[{"2": 3}, {"3": 3}], [169, 215], 2], [[{"2": 3}, {"1": 6}], [175, 309], 2], [[{"2": 5}, {"1": 3}], [179, 360], 2], [[{"2": 7}, {"1": 2}], [181, 197], 2], [[{"1": 2}, {"2": 2}], [182, 296, 351], 3], [[{"1": 3}, {"2": 1}], [192, 288, 332, 379], 4], [[{"1": 3}, {"2": 5}], [194, 320, 361, 371], 4], [[{"1": 1}, {"2": 7}], [196, 369], 2], [[{"1": 2}, {"2": 3}], [212, 260], 2], [[{"4": 1}, {"3": 2}], [217, 238], 2], [[{"3": 2}, {"2": 1}], [231, 373], 2], [[{"2": 4}, {"4": 1}], [257, 358], 2], [[{"1": 4}, {"2": 1}], [262, 316], 2], [[{"3": 1}, {"2": 2}, {"3": 1}], [7, 140], 2], [[{"4": 2}, {"3": 1}, {"2": 1}], [10, 114], 2], [[{"3": 1}, {"2": 1}, {"3": 3}], [11, 24], 2], [[{"2": 2}, {"3": 1}, {"2": 1}], [23, 75, 443], 3], [[{"2": 1}, {"3": 3}, {"2": 3}], [25, 167], 2], [[{"1": 1}, {"2": 1}, {"3": 1}], [30, 38, 160], 3], [[{"1": 3}, {"2": 3}, {"1": 1}], [36, 250], 2], [[{"2": 3}, {"1": 1}, {"2": 1}], [37, 251], 2], [[{"1": 4}, {"2": 2}, {"1": 1}], [46, 68], 2], [[{"2": 2}, {"1": 1}, {"2": 4}], [47, 293], 2], [[{"1": 1}, {"2": 4}, {"1": 2}], [48, 150, 294], 3], [[{"2": 4}, {"1": 2}, {"2": 7}], [49, 335], 2], [[{"2": 4}, {"1": 21}, {"2": 1}], [53, 491], 2], [[{"2": 2}, {"1": 2}, {"2": 1}], [59, 325, 343], 3], [[{"1": 2}, {"2": 1}, {"1": 1}], [60, 123, 198, 266, 326, 344], 6], [[{"2": 1}, {"1": 1}, {"2": 2}], [61, 228, 267, 285, 291, 299, 345, 380, 439], 9], [[{"1": 1}, {"2": 2}, {"1": 2}], [62, 300], 2], [[{"2": 1}, {"1": 4}, {"2": 2}], [67, 341], 2], [[{"3": 1}, {"2": 4}, {"3": 3}], [80, 142], 2], [[{"3": 1}, {"2": 1}, {"1": 1}], [96, 227, 438, 444, 462], 5], [[{"2": 1}, {"1": 1}, {"2": 3}], [97, 185, 463], 3], [[{"4": 1}, {"2": 1}, {"1": 2}], [121, 258], 2], [[{"2": 1}, {"1": 2}, {"2": 1}], [122, 165, 265], 3], [[{"1": 3}, {"2": 3}, {"1": 3}], [132, 190], 2], [[{"2": 3}, {"1": 3}, {"2": 2}], [133, 187], 2], [[{"1": 3}, {"2": 2}, {"1": 3}], [134, 188], 2], [[{"2": 4}, {"3": 1}, {"2": 1}], [137, 242], 2], [[{"2": 1}, {"3": 1}, {"2": 2}], [139, 161, 374], 3], [[{"2": 2}, {"3": 1}, {"2": 4}], [141, 240, 356], 3], [[{"2": 4}, {"1": 1}, {"2": 4}], [145, 392], 2], [[{"1": 2}, {"2": 4}, {"1": 1}], [152, 411], 2], [[{"2": 4}, {"1": 1}, {"2": 1}], [153, 209], 2], [[{"1": 1}, {"2": 1}, {"1": 3}], [154, 377], 2], [[{"1": 5}, {"2": 1}, {"1": 2}], [164, 387], 2], [[{"1": 2}, {"2": 2}, {"1": 1}], [182, 351], 2], [[{"2": 2}, {"1": 1}, {"2": 1}], [183, 376, 406], 3], [[{"1": 1}, {"2": 1}, {"1": 1}], [184, 284, 290], 3], [[{"1": 3}, {"2": 1}, {"1": 3}], [192, 332], 2], [[{"2": 4}, {"1": 3}, {"2": 4}], [207, 394], 2], [[{"1": 1}, {"2": 1}, {"1": 2}], [210, 264], 2], [[{"2": 1}, {"1": 2}, {"2": 3}], [211, 259], 2], [[{"1": 1}, {"2": 3}, {"1": 1}], [221, 270], 2], [[{"2": 1}, {"1": 1}, {"2": 1}], [263, 289, 327, 339], 4], [[{"1": 1}, {"2": 2}, {"1": 1}], [268, 292, 353], 3], [[{"1": 3}, {"2": 3}, {"1": 1}, {"2": 1}], [36, 250], 2], [[{"2": 2}, {"1": 1}, {"2": 4}, {"1": 2}], [47, 293], 2], [[{"2": 2}, {"1": 2}, {"2": 1}, {"1": 1}], [59, 325, 343], 3], [[{"1": 2}, {"2": 1}, {"1": 1}, {"2": 2}], [60, 266, 344], 3], [[{"2": 1}, {"1": 1}, {"2": 2}, {"1": 2}], [61, 299], 2], [[{"3": 1}, {"2": 1}, {"1": 1}, {"2": 3}], [96, 462], 2], [[{"2": 1}, {"1": 2}, {"2": 1}, {"1": 1}], [122, 265], 2], [[{"2": 3}, {"1": 3}, {"2": 2}, {"1": 3}], [133, 187], 2], [[{"2": 1}, {"1": 1}, {"2": 2}, {"1": 1}], [267, 291], 2], [[{"1": 1}, {"2": 1}, {"1": 1}, {"2": 2}], [284, 290], 2], [[{"2": 2}, {"1": 2}, {"2": 1}, {"1": 1}, {"2": 2}], [59, 343], 2]]