[[[{"1": 22}, {"2": 1}], [0, 191], 2], [[{"2": 1}, {"1": 4}], [1, 87, 119, 180], 4], [[{"1": 3}, {"2": 2}], [8, 238], 2], [[{"1": 13}, {"2": 1}], [12, 114, 261], 3], [[{"2": 1}, {"1": 10}], [13, 79], 2], [[{"2": 1}, {"1": 25}], [15, 149, 176, 194], 4], [[{"1": 25}, {"2": 3}], [16, 195], 2], [[{"2": 3}, {"1": 13}], [17, 260], 2], [[{"2": 2}, {"1": 2}], [19, 169, 244], 3], [[{"1": 2}, {"2": 1}], [20, 129, 131, 170, 183, 245], 6], [[{"1": 4}, {"2": 2}], [24, 120, 168], 3], [[{"2": 1}, {"1": 2}], [27, 99, 128, 130, 182], 5], [[{"1": 2}, {"2": 2}], [28, 110, 243], 3], [[{"3": 1}, {"2": 1}], [32, 118], 2], [[{"1": 9}, {"2": 1}], [34, 160], 2], [[{"2": 1}, {"3": 1}], [35, 60, 117, 136, 236, 241], 6], [[{"1": 1}, {"2": 2}], [37, 158, 213], 3], [[{"2": 2}, {"1": 7}], [38, 50, 56, 111], 4], [[{"1": 7}, {"2": 3}], [39, 82], 2], [[{"2": 3}, {"1": 7}], [40, 165], 2], [[{"1": 7}, {"2": 2}], [41, 53, 90, 112, 166, 185], 6], [[{"2": 2}, {"1": 8}], [42, 141, 198, 202], 4], [[{"1": 8}, {"2": 1}], [43, 146, 175, 189, 199], 5], [[{"2": 1}, {"1": 5}], [46, 48, 95, 171, 178, 210], 6], [[{"1": 5}, {"2": 1}], [47, 74, 96, 179, 207, 211], 6], [[{"1": 7}, {"2": 1}], [51, 57, 123, 209], 4], [[{"2": 1}, {"1": 7}], [52, 89, 124, 184, 208], 5], [[{"2": 1}, {"1": 1}], [63, 75, 77, 132, 161, 212], 6], [[{"1": 1}, {"2": 1}], [64, 76, 78, 84, 133, 152, 162, 219], 8], [[{"2": 1}, {"1": 6}], [65, 97, 200, 216], 4], [[{"1": 6}, {"2": 1}], [66, 98], 2], [[{"2": 1}, {"1": 15}], [85, 134], 2], [[{"1": 15}, {"2": 1}], [86, 135], 2], [[{"1": 4}, {"2": 1}], [88, 181], 2], [[{"2": 1}, {"1": 3}], [93, 115], 2], [[{"1": 3}, {"2": 1}], [94, 116, 127], 3], [[{"3": 1}, {"4": 1}], [101, 103], 2], [[{"2": 1}, {"1": 25}, {"2": 3}], [15, 194], 2], [[{"2": 2}, {"1": 2}, {"2": 1}], [19, 169, 244], 3], [[{"2": 3}, {"1": 7}, {"2": 2}], [40, 165], 2], [[{"2": 2}, {"1": 8}, {"2": 1}], [42, 198], 2], [[{"2": 1}, {"1": 5}, {"2": 1}], [46, 95, 178, 210], 4], [[{"2": 2}, {"1": 7}, {"2": 1}], [50, 56], 2], [[{"1": 7}, {"2": 1}, {"1": 7}], [51, 123], 2], [[{"2": 1}, {"1": 7}, {"2": 2}], [52, 89, 184], 3], [[{"2": 1}, {"1": 1}, {"2": 1}], [63, 75, 77, 132, 161], 5], [[{"2": 1}, {"1": 6}, {"2": 1}], [65, 97], 2], [[{"1": 1}, {"2": 1}, {"1": 15}], [84, 133], 2], [[{"2": 1}, {"1": 15}, {"2": 1}], [85, 134], 2], [[{"2": 1}, {"1": 4}, {"2": 1}], [87, 180], 2], [[{"2": 1}, {"1": 3}, {"2": 1}], [93, 115], 2], [[{"1": 1}, {"2": 1}, {"1": 15}, {"2": 1}], [84, 133], 2]]